[
  {"title":"Course Orientation","duration":"—","link":"https://usucourses.instructure.com/courses/2879/pages/course-orientation","module":"Orientation","id":"O-1-1"},
  {"title":"Overview of Doc Accessibility: Part 1","duration":"6:02","link":"https://usucourses.instructure.com/courses/2879/pages/overview-of-document-accessibility-part-1","module":"M1","id":"1-1-1"},
  {"title":"Overview of Doc Accessibility: Part 2","duration":"4:47","link":"https://usucourses.instructure.com/courses/2879/pages/overview-of-document-accessibility-part-2","module":"M1","id":"1-1-2"},
  {"title":"Images: Part 1","duration":"9:23","link":"https://usucourses.instructure.com/courses/2879/pages/images-part-1","module":"M1","id":"1-2-1"},
  {"title":"Images: Part 2","duration":"6:31","link":"https://usucourses.instructure.com/courses/2879/pages/images-part-2","module":"M1","id":"1-2-2"},
  {"title":"Images: Part 3","duration":"3:19","link":"https://usucourses.instructure.com/courses/2879/pages/images-part-3","module":"M1","id":"1-2-3"},
  {"title":"Optimizing Hyperlinks","duration":"4:46","link":"https://usucourses.instructure.com/courses/2879/pages/optimizing-hyperlinks","module":"M1","id":"1-3-1"},
  {"title":"Adding and Editing Hyperlinks","duration":"4:12","link":"https://usucourses.instructure.com/courses/2879/pages/adding-and-editing-hyperlinks","module":"M1","id":"1-3-2"},
  {"title":"Plain Language, Spelling, and Grammar","duration":"9:02","link":"https://usucourses.instructure.com/courses/2879/pages/plain-language-spelling-and-grammar","module":"M1","id":"1-5-1"},
  {"title":"Readability","duration":"4:35","link":"https://usucourses.instructure.com/courses/2879/pages/readability","module":"M1","id":"1-5-2"},
  {"title":"Legible Documents","duration":"4:45","link":"https://usucourses.instructure.com/courses/2879/pages/legible-documents","module":"M1","id":"1-5-3"},
  {"title":"The Importance of Headings","duration":"3:49","link":"https://usucourses.instructure.com/courses/2879/pages/the-importance-of-headings","module":"M2","id":"2-1-1"},
  {"title":"Creating Headings","duration":"5:27","link":"https://usucourses.instructure.com/courses/2879/pages/creating-headings","module":"M2","id":"2-1-2"},
  {"title":"Modifying Headings","duration":"3:16","link":"https://usucourses.instructure.com/courses/2879/pages/modifying-headings","module":"M2","id":"2-1-3"},
  {"title":"Tables of Contents","duration":"4:03","link":"https://usucourses.instructure.com/courses/2879/pages/tables-of-contents","module":"M2","id":"2-1-4"},
  {"title":"Themes & Layouts","duration":"6:31","link":"https://usucourses.instructure.com/courses/2879/pages/themes-and-layouts","module":"M2","id":"2-2-1"},
  {"title":"Slide Master","duration":"3:43","link":"https://usucourses.instructure.com/courses/2879/pages/slide-master","module":"M2","id":"2-2-2"},
  {"title":"Reading Order & Principles of Accessibility","duration":"6:01","link":"https://usucourses.instructure.com/courses/2879/pages/reading-order-and-principles-of-accessibility","module":"M2","id":"2-2-3"},
  {"title":"Tables","duration":"6:10","link":"https://usucourses.instructure.com/courses/2879/pages/tables","module":"M2","id":"2-4-1"},
  {"title":"Evaluating Accessibility","duration":"6:26","link":"https://usucourses.instructure.com/courses/2879/pages/evaluating-accessibility","module":"M3","id":"3-1-1"},
  {"title":"Practicing Evaluation & Repair","duration":"1:23","link":"https://usucourses.instructure.com/courses/2879/pages/practicing-evaluation-and-repair","module":"M3","id":"3-2-1"},
  {"title":"Filename & Document Title","duration":"3:18","link":"https://usucourses.instructure.com/courses/2879/pages/filename-and-document-title","module":"M3","id":"3-2-2"},
  {"title":"Creating PDFs: Part 1","duration":"4:04","link":"https://usucourses.instructure.com/courses/2879/pages/creating-pdfs-part-1","module":"M3","id":"3-3-1"},
  {"title":"Mac Users: Adobe's Cloud Service","duration":"3:05","link":"https://usucourses.instructure.com/courses/2879/pages/mac-users-adobes-cloud-service","module":"M3","id":"3-3-2"},
  {"title":"Creating PDFs: Part 2","duration":"2:28","link":"https://usucourses.instructure.com/courses/2879/pages/creating-pdfs-part-2","module":"M3","id":"3-3-3"},
  {"title":"Introduction to Optimizing PDFs: Part 1","duration":"3:31","link":"https://usucourses.instructure.com/courses/2879/pages/introduction-to-optimizing-pdfs-part-1","module":"M4","id":"4-1-1"},
  {"title":"Introduction to Optimizing PDFs: Part 2","duration":"5:28","link":"https://usucourses.instructure.com/courses/2879/pages/introduction-to-optimizing-pdfs-part-2","module":"M4","id":"4-1-2"},
  {"title":"Checking Accessibility","duration":"7:41","link":"https://usucourses.instructure.com/courses/2879/pages/checking-accessibility","module":"M4","id":"4-2-1"},
  {"title":"Reading Order Tool","duration":"6:08","link":"https://usucourses.instructure.com/courses/2879/pages/reading-order-tool","module":"M4","id":"4-3-1"},
  {"title":"Content Order and Tags Order","duration":"6:15","link":"https://usucourses.instructure.com/courses/2879/pages/content-order-and-tags-order","module":"M4","id":"4-4-1"},
  {"title":"Navigating in Excel","duration":"7:32","link":"https://usucourses.instructure.com/courses/2879/pages/navigating-in-excel","module":"M5","id":"5-1-1"},
  {"title":"Sheets & Tables","duration":"8:26","link":"https://usucourses.instructure.com/courses/2879/pages/sheets-and-tables","module":"M5","id":"5-2-1"},
  {"title":"Images & Links","duration":"5:36","link":"https://usucourses.instructure.com/courses/2879/pages/images-and-links","module":"M5","id":"5-3-1"},
  {"title":"Creating Accessible Charts: Part 1","duration":"10:12","link":"https://usucourses.instructure.com/courses/2879/pages/creating-accessible-charts-part-1","module":"M5","id":"5-4-1"},
  {"title":"Creating Accessible Charts: Part 2","duration":"7:52","link":"https://usucourses.instructure.com/courses/2879/pages/creating-accessible-charts-part-2","module":"M5","id":"5-4-2"},
  {"title":"Creating Accessible Charts: Part 3","duration":"10:00","link":"https://usucourses.instructure.com/courses/2879/pages/creating-accessible-charts-part-3","module":"M5","id":"5-4-3"},
  {"title":"Optimizing Workbooks","duration":"9:54","link":"https://usucourses.instructure.com/courses/2879/pages/optimizing-workbooks","module":"M5","id":"5-5-1"},
  {"title":"Evaluating Accessibility in Excel","duration":"4:50","link":"https://usucourses.instructure.com/courses/2879/pages/evaluating-accessibility-in-excel","module":"M5","id":"5-6-1"}
]
